{"P1": "org:dissolved", "P2": "org:founded", "P3": "org:place_of_headquarters", "P4": "org:alternate_names", "P5": "org:member_of", "P6": "org:members", "P7": "org:political/religious_affiliation", "P8": "org:product", "P9": "org:founded_by", "P10": "org:top_members/employees", "P11": "per:place_of_birth", "P12": "per:place_of_death", "P13": "per:place_of_residence", "P14": "per:origin", "P15": "per:employee_of", "P16": "per:schools_attended", "P17": "per:alternate_names", "P18": "per:parents", "P19": "per:children", "P20": "per:siblings", "P21": "per:spouse", "P22": "per:other_family", "P23": "per:colleagues", "P24": "per:product", "P25": "per:religion", "P26": "per:title"}